cogment/__init__.py
cogment/actor.py
cogment/agent_service.py
cogment/client_service.py
cogment/context.py
cogment/control.py
cogment/datalog.py
cogment/datalog_service.py
cogment/datastore.py
cogment/directory.py
cogment/endpoints.py
cogment/env_service.py
cogment/environment.py
cogment/errors.py
cogment/generate.py
cogment/grpc_metadata.py
cogment/hooks_service.py
cogment/model_registry.py
cogment/model_registry_v2.py
cogment/parameters.py
cogment/prehook.py
cogment/session.py
cogment/trial.py
cogment/utils.py
cogment/version.py
cogment/api/agent.proto
cogment/api/agent_pb2.py
cogment/api/agent_pb2_grpc.py
cogment/api/common.proto
cogment/api/common_pb2.py
cogment/api/common_pb2_grpc.py
cogment/api/datalog.proto
cogment/api/datalog_pb2.py
cogment/api/datalog_pb2_grpc.py
cogment/api/directory.proto
cogment/api/directory_pb2.py
cogment/api/directory_pb2_grpc.py
cogment/api/environment.proto
cogment/api/environment_pb2.py
cogment/api/environment_pb2_grpc.py
cogment/api/hooks.proto
cogment/api/hooks_pb2.py
cogment/api/hooks_pb2_grpc.py
cogment/api/model_registry.proto
cogment/api/model_registry_pb2.py
cogment/api/model_registry_pb2_grpc.py
cogment/api/orchestrator.proto
cogment/api/orchestrator_pb2.py
cogment/api/orchestrator_pb2_grpc.py
cogment/api/trial_datastore.proto
cogment/api/trial_datastore_pb2.py
cogment/api/trial_datastore_pb2_grpc.py
cogment-2.10.1.data/data/CHANGELOG.md
cogment-2.10.1.dist-info/LICENSE
cogment-2.10.1.dist-info/METADATA
cogment-2.10.1.dist-info/WHEEL
cogment-2.10.1.dist-info/top_level.txt
cogment-2.10.1.dist-info/RECORD
