Metadata-Version: 2.1
Name: cogment
Version: 2.10.1
Summary: Cogment python SDK
Author-email: Artificial Intelligence Redefined <dev+cogment@ai-r.com>
Project-URL: Homepage, https://cogment.ai
Project-URL: repository, https://github.com/cogment/cogment-py-sdk
Project-URL: Reference Documentation, https://cogment.ai/docs/reference/python
Classifier: Programming Language :: Python :: 3
Classifier: Development Status :: 5 - Production/Stable
Classifier: License :: OSI Approved :: Apache Software License
Classifier: Operating System :: OS Independent
Requires-Python: <3.11,>=3.7
License-File: LICENSE
Requires-Dist: grpcio <1.49,>=1.42
Requires-Dist: grpcio-reflection <1.49,>=1.42
Requires-Dist: protobuf <4.0,>=3.7
Requires-Dist: prometheus-client <0.9,>=0.8
Requires-Dist: typing-extensions <4.7.0,>=4.6.3
Provides-Extra: generate
Requires-Dist: PyYaml <6.1,>=5.3.1 ; extra == 'generate'
Requires-Dist: psutil ~=5.9 ; extra == 'generate'
Requires-Dist: grpcio-tools <1.49,>=1.42 ; extra == 'generate'
Requires-Dist: click ~=8.0.3 ; extra == 'generate'
